chargespot/__init__.py
chargespot/api_decorator.py
chargespot/cli.py
chargespot/config_manager.py
chargespot/email_report_template.html
chargespot/exceptions.py
chargespot/execute.py
chargespot/heman_datetime.py
chargespot/report.py
chargespot/swagger.py
chargespot/utils.py
chargespot/templates/.chargespot
chargespot/templates/.gitignore
chargespot/templates/README.md
chargespot/templates/config.yaml
chargespot/templates/requirements.txt
chargespot/templates/api/__init__.py
chargespot/templates/api/demo.py
chargespot/templates/common/__init__.py
chargespot/templates/common/assert_tools.py
chargespot/templates/db/__init__.py
chargespot/templates/report/.gitkeep
chargespot/templates/test_suites/__init__.py
chargespot/templates/test_suites/test_book_list.py
chargespot/templates/test_suites/test_login.py
chargespot-0.0.4.dist-info/LICENSE
chargespot-0.0.4.dist-info/METADATA
chargespot-0.0.4.dist-info/WHEEL
chargespot-0.0.4.dist-info/entry_points.txt
chargespot-0.0.4.dist-info/top_level.txt
chargespot-0.0.4.dist-info/RECORD
